pyimage2pdf/CommandClass.py
pyimage2pdf/Preferences.py
pyimage2pdf/PyImage2Pdf.py
pyimage2pdf/__init__.py
pyimage2pdf/_version.py
pyimage2pdf/py.typed
pyimage2pdf/resources/__init__.py
pyimage2pdf/resources/loggingConfiguration.json
pyimage2pdf/resources/py.typed
pyimage2pdf-1.0.3.dist-info/LICENSE
pyimage2pdf-1.0.3.dist-info/METADATA
pyimage2pdf-1.0.3.dist-info/WHEEL
pyimage2pdf-1.0.3.dist-info/entry_points.txt
pyimage2pdf-1.0.3.dist-info/top_level.txt
pyimage2pdf-1.0.3.dist-info/RECORD
