Metadata-Version: 2.2
Name: pyimage2pdf
Version: 1.0.3
Summary: An adapter
Author-email: "Humberto A. Sanchez II" <Humberto.A.Sanchez.II@gmail.com>
Maintainer-email: "Humberto A. Sanchez II" <Humberto.A.Sanchez.II@gmail.com>
License: GNU AFFERO GENERAL PUBLIC LICENSE
Project-URL: Repository, https://github.com/hasii2011/pyimage2pdf
Keywords: pyut,images,adapter,pdf
Classifier: Programming Language :: Python
Classifier: Intended Audience :: Developers
Classifier: License :: OSI Approved :: GNU Affero General Public License v3
Classifier: Operating System :: MacOS :: MacOS X
Classifier: Topic :: Software Development :: Libraries :: Python Modules
License-File: LICENSE
Requires-Dist: codeallybasic>=1.8.5
Requires-Dist: click>=8.1.8
Requires-Dist: pillow==11.0.0
Requires-Dist: pypdf>=5.1.0
Provides-Extra: test
Requires-Dist: html-testRunner~=1.2.1; extra == "test"
Requires-Dist: mypy==1.14.0; extra == "test"
Requires-Dist: buildlackey==1.8.0; extra == "test"
Provides-Extra: deploy
Requires-Dist: wheel==0.45.1; extra == "deploy"
Requires-Dist: setuptools==75.7.0; extra == "deploy"
Requires-Dist: twine==6.0.1; extra == "deploy"
Requires-Dist: build==1.2.2.post1; extra == "deploy"
